COPYING
MANIFEST.in
setup.py
docs/source/api.rst
docs/source/changelog.rst
docs/source/conf.py
docs/source/contrib.rst
docs/source/index.rst
jsonstruct/__init__.py
jsonstruct/_handlers.py
jsonstruct/_samples.py
jsonstruct/backend.py
jsonstruct/compat.py
jsonstruct/handlers.py
jsonstruct/pickler.py
jsonstruct/tags.py
jsonstruct/unpickler.py
jsonstruct/util.py
jsonstruct/version.py
jsonstruct.egg-info/PKG-INFO
jsonstruct.egg-info/SOURCES.txt
jsonstruct.egg-info/dependency_links.txt
jsonstruct.egg-info/top_level.txt
tests/backends_tests.py
tests/benchmark.py
tests/document_test.py
tests/jsonstruct_test.py
tests/runtests.py
tests/test_datetime.py
tests/test_handlers.py
tests/thirdparty_tests.py
tests/util_tests.py